  {
    "reviewer_name": "Lizzie",
    "reviewer_id": "36036358",
    "date": "2015/08/23",
    "comments": "El piso era exactamente como lo describió Candy, y las fotos también. Lo que aprecié es que estaba muy limpio y mi habitación era lo suficientemente amplia con una cama muy cómoda. Además, fue muy tranquilo para dormir, disfruté de mi estancia aquí en Nueva York. Solo pasaron 2 noches, así que no vi a Candy, ya que siempre salía, pero Candy fue muy amable y servicial :) Gracias nuevamente Candy!",
    "host_name": "Candy",
    "host_id": "36656552"
   } 
