  {
    "reviewer_name": "Matt",
    "reviewer_id": "2554048",
    "date": "2013/01/04",
    "comments": "Robert fue un gran anfitrión, muy amigable, fácil de chatear, dio excelentes consejos y su apartamento está ubicado justo donde quieres estar. Muy cerca de Times Square, con la posibilidad de alejarse de todo para disfrutar de una buena comida en Hell's Kitchen. Blazer, el perro, es realmente bueno tenerlo en la casa también. Definitivamente recomendaría una estancia con Robert a cualquiera que busque un buen momento en la Gran Manzana.",
    "host_name": "Robert",
    "host_id": "2743623"
   } 
