  {
    "reviewer_name": "Simon",
    "reviewer_id": "32488952",
    "date": "2015/10/03",
    "comments": "Nos alojamos en Candy durante una semana. El apartamento fue realmente genial! La habitación estaba limpia, totalmente renovada, ... No pasamos mucho tiempo en el apartamento, porque estábamos visitando todo el día. Candy estuvo bien, se aseguró de que tuviéramos todo para ser felices. La ubicación es excelente. Hay una estación de metro en 2 minutos. El vecindario es tranquilo (excepto cuando llueve;)) ¡Gracias por todo!",
    "host_name": "Candy",
    "host_id": "36656552"
   } 
